InfrontConnect
