Metadata-Version: 1.0
Name: InfrontConnect
Version: 1.0.11
Summary: Infront Desktop API for Python 3
Home-page: UNKNOWN
Author: Infront ASA
Author-email: alan.lucero@infrontfinance.com
License: MIT
Keywords: infront desktop API finance
Platform: UNKNOWN
